unit_bpe-0.2.0.dist-info/METADATA
unit_bpe-0.2.0.dist-info/WHEEL
unit_bpe-0.2.0.dist-info/licenses/LICENSE
unit_bpe/__init__.py
unit_bpe/unit_bpe.cpython-39-aarch64-linux-gnu.so
unit_bpe-0.2.0.dist-info/RECORD
