Metadata-Version: 2.3
Name: unit-bpe
Version: 0.2.0
License-File: LICENSE
Summary: BPE tokenizer that operates on integer sequences
Requires-Python: >=3.9
